{
	"info": {
		"_postman_id": "a2320e34-e137-4e4e-b224-af5b3d42528e",
		"name": "Sample With variables",
		"schema": "https://schema.getpostman.com/json/collection/v2.1.0/collection.json"
	},
	"item": [],
	"event": [
		{
			"listen": "prerequest",
			"script": {
				"type": "text/javascript",
				"exec": [
					""
				]
			}
		},
		{
			"listen": "test",
			"script": {
				"type": "text/javascript",
				"exec": [
					""
				]
			}
		}
	],
	"variable": [
		{
			"key": "host",
			"value": "http://localhost"
		},
		{
			"key": "port",
			"value": "8080"
		},
		{
			"key": "username",
			"value": "testuser"
		},
		{
			"key": "password",
			"value": "secret"
		}
	]
}